thunderhopper/__init__.py
thunderhopper/arraytools.py
thunderhopper/filetools.py
thunderhopper/filters.py
thunderhopper/filtertools.py
thunderhopper/labeltools.py
thunderhopper/misctools.py
thunderhopper/model.py
thunderhopper/modeltools.py
thunderhopper/plottools.py
thunderhopper/spatialtools.py
thunderhopper/stats.py
thunderhopper/version.py
thunderhopper-1.0.1.dist-info/licenses/LICENSE
thunderhopper-1.0.1.dist-info/METADATA
thunderhopper-1.0.1.dist-info/WHEEL
thunderhopper-1.0.1.dist-info/top_level.txt
thunderhopper-1.0.1.dist-info/RECORD
