Metadata-Version: 2.4
Name: thunderhopper
Version: 1.0.1
Summary: Model of the auditory pathway of grasshoppers.
Author-email: Jona Hartling <jona.hartling@uni-tuebingen.de>
Maintainer-email: Jona Hartling <jona.hartling@uni-tuebingen.de>, Jan Benda <jan.benda@uni-tuebingen.de>
License:                     GNU AFFERO GENERAL PUBLIC LICENSE
Project-URL: Repository, https://github.com/bendalab/thunderhopper
Project-URL: Documentation, https://bendalab.github.io/thunderhopper
Classifier: Development Status :: 4 - Beta
Classifier: Environment :: Console
Classifier: Intended Audience :: Science/Research
Classifier: License :: OSI Approved :: GNU General Public License v3 (GPLv3)
Classifier: Natural Language :: English
Classifier: Programming Language :: Python :: 3
Classifier: Programming Language :: Python :: 3.8
Classifier: Programming Language :: Python :: 3.12
Classifier: Operating System :: OS Independent
Classifier: Topic :: Multimedia :: Sound/Audio
Classifier: Topic :: Multimedia :: Sound/Audio :: Analysis
Classifier: Topic :: Scientific/Engineering
Classifier: Topic :: Software Development :: Libraries :: Python Modules
Requires-Python: >=3.6
License-File: LICENSE
Requires-Dist: scikit-learn
Requires-Dist: scipy
Requires-Dist: numpy
Requires-Dist: matplotlib
Requires-Dist: distinctipy
Requires-Dist: bottleneck
Requires-Dist: audioio>=2.5
Dynamic: license-file
